django_nameko_standalone/__init__.py
nameko_django_orm-2.0.4.dist-info/LICENSE
nameko_django_orm-2.0.4.dist-info/METADATA
nameko_django_orm-2.0.4.dist-info/WHEEL
nameko_django_orm-2.0.4.dist-info/top_level.txt
nameko_django_orm-2.0.4.dist-info/RECORD
